{
    "arch": "arm64",
    "build": "h76d750c_0",
    "build_number": 0,
    "channel": "conda-forge",
    "depends": [
        "libzlib >=1.2.13,<1.3.0a0"
    ],
    "fn": "libsqlite-3.40.0-h76d750c_0.tar.bz2",
    "license": "Unlicense",
    "md5": "d090fcec993f4ef0a90e6df7f231a273",
    "name": "libsqlite",
    "platform": "osx",
    "sha256": "5e8992b2099bb4767996e1bed70945ba39f61399ab912ba2a2770d12c165acb5",
    "size": 823390,
    "subdir": "osx-arm64",
    "timestamp": 1668697846097,
    "url": "https://conda.anaconda.org/conda-forge/osx-arm64/libsqlite-3.40.0-h76d750c_0.tar.bz2",
    "version": "3.40.0"
}